st_picture_carousel/__init__.py
st_picture_carousel/frontend/index.html
st_picture_carousel/frontend/main.js
st_picture_carousel/frontend/streamlit-component-lib.js
st_picture_carousel/frontend/style.css
st_picture_carousel/frontend/carousel/carousel.css
st_picture_carousel/frontend/carousel/carousel.html
st_picture_carousel/frontend/carousel/carousel.js
streamlit_picture_carousel-0.1.5.dist-info/LICENSE
streamlit_picture_carousel-0.1.5.dist-info/METADATA
streamlit_picture_carousel-0.1.5.dist-info/WHEEL
streamlit_picture_carousel-0.1.5.dist-info/top_level.txt
streamlit_picture_carousel-0.1.5.dist-info/RECORD
