Metadata-Version: 2.1
Name: streamlit-picture-carousel
Version: 0.1.5
Summary: Displays 3d carousel of pictures
Author: Rafal Cegiela
Author-email: rcegiela@gmail.com
Requires-Python: >=3.7
License-File: LICENSE
Requires-Dist: streamlit (>=1.2)
Requires-Dist: jinja2
